{
  "schema_version": 1,
  "checkpoint_id": 3,
  "state": "implementing",
  "iteration": 1,
  "transitions": [
    {
      "from": "selecting_issue",
      "to": "preparing_worktree",
      "iteration": 0,
      "elapsed_ms": 390,
      "reason": "issue validated and claimed"
    },
    {
      "from": "preparing_worktree",
      "to": "planning",
      "iteration": 0,
      "elapsed_ms": 820,
      "reason": "worktree ready, endpoints healthy"
    },
    {
      "from": "planning",
      "to": "implementing",
      "iteration": 1,
      "elapsed_ms": 821,
      "reason": "iteration 1 planned, tier=Worker"
    }
  ],
  "created_at": "2026-04-15T02:55:33.083590164+00:00",
  "git_hash": "e0ad31b3a32c8b54d73257b1413c678f8b2a9fe6",
  "issue_id": "beefcake-ek56e"
}